{
    "class": "mkbase.memoView",
    "type": "EXTENSION",
    "extends": "mkbase.memo",
    "views": [
        {
            "defaultView": true,
            "relationView": true,
            "defaultSort": "datum,desc",
            "values": [
                { "name": "datum" },
                { "name": "opmerking" },
                { "name": "kernwoord" },
                { "name": "schrijverMemo" },
                { "name": "resultaatContact" },
                { "name": "followUp" },
                { "type": "RELATION", "relatedClass": "mkbase.entiteit" }
            ]
        }
    ],
    "translations": [
        {
            "language": "en",
            "plural": "memos"
        }
    ]
}