{
  "class" : "mkbase.mogelijkeMatch",
  "type" : "BASIC",
  "valueTypes" : [ {
    "name" : "mogelijkeMatch",
    "dataType" : "LIST",
    "enabled" : true,
    "required" : true,
    "list" : null
  }, {
    "name" : "memoDossier",
    "dataType" : "TEXTBLOCK",
    "enabled" : true,
    "required" : false,
    "list" : null
  }, {
    "name" : "omschrijving",
    "dataType" : "TEXT",
    "enabled" : true,
    "required" : false,
    "list" : null
  }, {
    "name" : "samenvatting",
    "dataType" : "TEXT",
    "enabled" : true,
    "required" : false,
    "list" : null
  } ],
  "relations" : [ {
    "type" : "mkbase.koper",
    "required" : true,
    "multiple" : false,
    "cascadeDelete" : false
  }, {
    "type" : "mkbase.verkoper",
    "required" : true,
    "multiple" : false,
    "cascadeDelete" : false
  } ],
  "inherits" : "mkbase.mappensysteem"
}